esp_linker/__init__.py
esp_linker/cli.py
esp_linker/dashboard.py
esp_linker/device_manager.py
esp_linker/espboard.py
esp_linker/exceptions.py
esp_linker/flasher.py
esp_linker/logger.py
esp_linker/utils.py
esp_linker/version.py
esp_linker/wifi_wizard.py
esp_linker/firmware/esp-linker-firmware.bin
esp_linker-1.3.7.dist-info/METADATA
esp_linker-1.3.7.dist-info/WHEEL
esp_linker-1.3.7.dist-info/entry_points.txt
esp_linker-1.3.7.dist-info/top_level.txt
esp_linker-1.3.7.dist-info/RECORD
