Metadata-Version: 2.1
Name: esp-linker
Version: 1.3.7
Summary: Professional wireless GPIO control for ESP8266 boards with PyFirmata-inspired interface
Home-page: https://www.skrelectronicslab.com
Download-URL: https://pypi.org/project/esp-linker/
Author: SK Raihan
Author-email: SK Raihan <skrelectronicslab@gmail.com>
Maintainer: SKR Electronics Lab
Maintainer-email: SK Raihan <skrelectronicslab@gmail.com>
Project-URL: Homepage, https://github.com/skr-electronics-lab/esp-linker
Project-URL: Documentation, https://github.com/skr-electronics-lab/esp-linker#readme
Project-URL: Repository, https://github.com/skr-electronics-lab/esp-linker.git
Project-URL: Bug Tracker, https://github.com/skr-electronics-lab/esp-linker/issues
Project-URL: Changelog, https://github.com/skr-electronics-lab/esp-linker/blob/main/CHANGELOG.md
Project-URL: Author Website, https://www.skrelectronicslab.com
Project-URL: YouTube Channel, https://www.youtube.com/@skr_electronics_lab
Project-URL: Instagram, https://www.instagram.com/skr_electronics_lab
Project-URL: Support, https://buymeacoffee.com/skrelectronics
Keywords: esp8266,esp32,gpio,iot,wireless,arduino,microcontroller,automation,robotics,electronics,maker,diy,wifi,remote control
Classifier: Development Status :: 5 - Production/Stable
Classifier: Intended Audience :: Developers
Classifier: Intended Audience :: Education
Classifier: Intended Audience :: Science/Research
Classifier: Operating System :: OS Independent
Classifier: Programming Language :: Python :: 3
Classifier: Programming Language :: Python :: 3.7
Classifier: Programming Language :: Python :: 3.8
Classifier: Programming Language :: Python :: 3.9
Classifier: Programming Language :: Python :: 3.10
Classifier: Programming Language :: Python :: 3.11
Classifier: Programming Language :: Python :: 3.12
Classifier: Topic :: Software Development :: Libraries :: Python Modules
Classifier: Topic :: System :: Hardware
Classifier: Topic :: Home Automation
Classifier: Topic :: Scientific/Engineering
Classifier: Topic :: Education
Requires-Python: >=3.7
Requires-Dist: requests>=2.25.0
Requires-Dist: pyserial>=3.5
Requires-Dist: zeroconf>=0.38.0
Requires-Dist: tqdm>=4.62.0
Requires-Dist: colorama>=0.4.4
Requires-Dist: flask>=2.0.0
Requires-Dist: flask-cors>=3.0.10
Requires-Dist: esptool>=4.0.0
Provides-Extra: all
Requires-Dist: flask>=2.0.0; extra == "all"
Requires-Dist: zeroconf>=0.38.0; extra == "all"
Provides-Extra: dashboard
Requires-Dist: flask>=2.0.0; extra == "dashboard"
Provides-Extra: dev
Requires-Dist: pytest>=6.0; extra == "dev"
Requires-Dist: pytest-cov>=2.0; extra == "dev"
Requires-Dist: black>=21.0; extra == "dev"
Requires-Dist: flake8>=3.8; extra == "dev"
Requires-Dist: mypy>=0.800; extra == "dev"
Requires-Dist: build>=0.7.0; extra == "dev"
Requires-Dist: twine>=3.4.0; extra == "dev"
